django_elastic_appsearch/__init__.py
django_elastic_appsearch/apps.py
django_elastic_appsearch/clients.py
django_elastic_appsearch/orm.py
django_elastic_appsearch/serialisers.py
django_elastic_appsearch/slicer.py
django_elastic_appsearch/test.py
django_elastic_appsearch-2.1.0.dist-info/AUTHORS.rst
django_elastic_appsearch-2.1.0.dist-info/LICENSE
django_elastic_appsearch-2.1.0.dist-info/METADATA
django_elastic_appsearch-2.1.0.dist-info/WHEEL
django_elastic_appsearch-2.1.0.dist-info/top_level.txt
django_elastic_appsearch-2.1.0.dist-info/RECORD
