Metadata-Version: 2.1
Name: django-elastic-appsearch
Version: 2.1.0
Summary: Integrate your Django Project with Elastic App Search with ease.
Home-page: https://github.com/infoxchange/django_elastic_appsearch
Author: Infoxchange
Author-email: devs@infoxchange.org
License: MIT
Keywords: django_elastic_appsearch
Classifier: Development Status :: 5 - Production/Stable
Classifier: Framework :: Django :: 2.2
Classifier: Framework :: Django :: 3.0
Classifier: Framework :: Django :: 3.1
Classifier: Framework :: Django :: 3.2
Classifier: Intended Audience :: Developers
Classifier: License :: OSI Approved :: MIT License
Classifier: Natural Language :: English
Classifier: Programming Language :: Python :: 3.6
Classifier: Programming Language :: Python :: 3.7
Classifier: Programming Language :: Python :: 3.8
Classifier: Programming Language :: Python :: 3.9
License-File: LICENSE
License-File: AUTHORS.rst
Requires-Dist: elastic-enterprise-search >=7.15.0
Requires-Dist: serpy
